{
  "apps/api": {
    "root": [
      "apps/api/package.json",
      "nx/core/package-json"
    ],
    "targets": [
      "apps/api/tsconfig.json",
      "@nx/js/typescript"
    ],
    "targets.typecheck": [
      "apps/api/tsconfig.json",
      "@nx/js/typescript"
    ],
    "targets.typecheck.dependsOn": [
      "apps/api/tsconfig.json",
      "@nx/js/typescript"
    ],
    "targets.typecheck.options": [
      "apps/api/tsconfig.json",
      "@nx/js/typescript"
    ],
    "targets.typecheck.cache": [
      "apps/api/tsconfig.json",
      "@nx/js/typescript"
    ],
    "targets.typecheck.inputs": [
      "apps/api/tsconfig.json",
      "@nx/js/typescript"
    ],
    "targets.typecheck.outputs": [
      "apps/api/tsconfig.json",
      "@nx/js/typescript"
    ],
    "targets.typecheck.syncGenerators": [
      "apps/api/tsconfig.json",
      "@nx/js/typescript"
    ],
    "targets.typecheck.metadata": [
      "apps/api/tsconfig.json",
      "@nx/js/typescript"
    ],
    "targets.typecheck.executor": [
      "apps/api/tsconfig.json",
      "@nx/js/typescript"
    ],
    "targets.typecheck.options.cwd": [
      "apps/api/tsconfig.json",
      "@nx/js/typescript"
    ],
    "targets.typecheck.options.command": [
      "apps/api/tsconfig.json",
      "@nx/js/typescript"
    ],
    "targets.typecheck.metadata.technologies": [
      "apps/api/tsconfig.json",
      "@nx/js/typescript"
    ],
    "targets.typecheck.metadata.technologies.0": [
      "apps/api/tsconfig.json",
      "@nx/js/typescript"
    ],
    "targets.typecheck.metadata.description": [
      "apps/api/tsconfig.json",
      "@nx/js/typescript"
    ],
    "targets.typecheck.metadata.help": [
      "apps/api/tsconfig.json",
      "@nx/js/typescript"
    ],
    "targets.typecheck.metadata.help.command": [
      "apps/api/tsconfig.json",
      "@nx/js/typescript"
    ],
    "targets.typecheck.metadata.help.example": [
      "apps/api/tsconfig.json",
      "@nx/js/typescript"
    ],
    "projectType": [
      "apps/api/webpack.config.js",
      "@nx/webpack/plugin"
    ],
    "targets.build": [
      "apps/api/package.json",
      "nx/core/package-json"
    ],
    "targets.build.options": [
      "apps/api/package.json",
      "nx/core/package-json"
    ],
    "targets.build.cache": [
      "apps/api/webpack.config.js",
      "@nx/webpack/plugin"
    ],
    "targets.build.dependsOn": [
      "apps/api/webpack.config.js",
      "@nx/webpack/plugin"
    ],
    "targets.build.inputs": [
      "apps/api/webpack.config.js",
      "@nx/webpack/plugin"
    ],
    "targets.build.outputs": [
      "apps/api/webpack.config.js",
      "@nx/webpack/plugin"
    ],
    "targets.build.metadata": [
      "apps/api/webpack.config.js",
      "@nx/webpack/plugin"
    ],
    "targets.build.syncGenerators": [
      "apps/api/webpack.config.js",
      "@nx/webpack/plugin"
    ],
    "targets.build.executor": [
      "apps/api/package.json",
      "nx/core/package-json"
    ],
    "targets.build.options.cwd": [
      "apps/api/package.json",
      "nx/core/package-json"
    ],
    "targets.build.options.args": [
      "apps/api/package.json",
      "nx/core/package-json"
    ],
    "targets.build.options.command": [
      "apps/api/package.json",
      "nx/core/package-json"
    ],
    "targets.build.metadata.technologies": [
      "apps/api/webpack.config.js",
      "@nx/webpack/plugin"
    ],
    "targets.build.metadata.technologies.0": [
      "apps/api/webpack.config.js",
      "@nx/webpack/plugin"
    ],
    "targets.build.metadata.description": [
      "apps/api/webpack.config.js",
      "@nx/webpack/plugin"
    ],
    "targets.build.metadata.help": [
      "apps/api/webpack.config.js",
      "@nx/webpack/plugin"
    ],
    "targets.build.metadata.help.command": [
      "apps/api/webpack.config.js",
      "@nx/webpack/plugin"
    ],
    "targets.build.metadata.help.example": [
      "apps/api/webpack.config.js",
      "@nx/webpack/plugin"
    ],
    "targets.preview": [
      "apps/api/webpack.config.js",
      "@nx/webpack/plugin"
    ],
    "targets.preview.continuous": [
      "apps/api/webpack.config.js",
      "@nx/webpack/plugin"
    ],
    "targets.preview.options": [
      "apps/api/webpack.config.js",
      "@nx/webpack/plugin"
    ],
    "targets.preview.metadata": [
      "apps/api/webpack.config.js",
      "@nx/webpack/plugin"
    ],
    "targets.preview.syncGenerators": [
      "apps/api/webpack.config.js",
      "@nx/webpack/plugin"
    ],
    "targets.preview.executor": [
      "apps/api/webpack.config.js",
      "@nx/webpack/plugin"
    ],
    "targets.preview.options.cwd": [
      "apps/api/webpack.config.js",
      "@nx/webpack/plugin"
    ],
    "targets.preview.options.args": [
      "apps/api/webpack.config.js",
      "@nx/webpack/plugin"
    ],
    "targets.preview.options.command": [
      "apps/api/webpack.config.js",
      "@nx/webpack/plugin"
    ],
    "targets.preview.metadata.technologies": [
      "apps/api/webpack.config.js",
      "@nx/webpack/plugin"
    ],
    "targets.preview.metadata.technologies.0": [
      "apps/api/webpack.config.js",
      "@nx/webpack/plugin"
    ],
    "targets.preview.metadata.description": [
      "apps/api/webpack.config.js",
      "@nx/webpack/plugin"
    ],
    "targets.preview.metadata.help": [
      "apps/api/webpack.config.js",
      "@nx/webpack/plugin"
    ],
    "targets.preview.metadata.help.command": [
      "apps/api/webpack.config.js",
      "@nx/webpack/plugin"
    ],
    "targets.preview.metadata.help.example": [
      "apps/api/webpack.config.js",
      "@nx/webpack/plugin"
    ],
    "targets.build-deps": [
      "apps/api/webpack.config.js",
      "@nx/webpack/plugin"
    ],
    "targets.build-deps.dependsOn": [
      "apps/api/webpack.config.js",
      "@nx/webpack/plugin"
    ],
    "targets.watch-deps": [
      "apps/api/webpack.config.js",
      "@nx/webpack/plugin"
    ],
    "targets.watch-deps.continuous": [
      "apps/api/webpack.config.js",
      "@nx/webpack/plugin"
    ],
    "targets.watch-deps.dependsOn": [
      "apps/api/webpack.config.js",
      "@nx/webpack/plugin"
    ],
    "targets.watch-deps.executor": [
      "apps/api/webpack.config.js",
      "@nx/webpack/plugin"
    ],
    "targets.watch-deps.options": [
      "apps/api/webpack.config.js",
      "@nx/webpack/plugin"
    ],
    "targets.watch-deps.options.command": [
      "apps/api/webpack.config.js",
      "@nx/webpack/plugin"
    ],
    "name": [
      "apps/api/package.json",
      "nx/core/package-json"
    ],
    "tags": [
      "apps/api/package.json",
      "nx/core/package-json"
    ],
    "tags.npm:private": [
      "apps/api/package.json",
      "nx/core/package-json"
    ],
    "metadata.targetGroups": [
      "apps/api/package.json",
      "nx/core/package-json"
    ],
    "metadata.js": [
      "apps/api/package.json",
      "nx/core/package-json"
    ],
    "metadata.js.packageName": [
      "apps/api/package.json",
      "nx/core/package-json"
    ],
    "metadata.js.packageVersion": [
      "apps/api/package.json",
      "nx/core/package-json"
    ],
    "metadata.js.isInPackageManagerWorkspaces": [
      "apps/api/package.json",
      "nx/core/package-json"
    ],
    "targets.build.configurations": [
      "apps/api/package.json",
      "nx/core/package-json"
    ],
    "targets.build.configurations.development": [
      "apps/api/package.json",
      "nx/core/package-json"
    ],
    "targets.build.configurations.development.args": [
      "apps/api/package.json",
      "nx/core/package-json"
    ],
    "targets.prune-lockfile": [
      "apps/api/package.json",
      "nx/core/package-json"
    ],
    "targets.prune-lockfile.dependsOn": [
      "apps/api/package.json",
      "nx/core/package-json"
    ],
    "targets.prune-lockfile.cache": [
      "apps/api/package.json",
      "nx/core/package-json"
    ],
    "targets.prune-lockfile.executor": [
      "apps/api/package.json",
      "nx/core/package-json"
    ],
    "targets.prune-lockfile.outputs": [
      "apps/api/package.json",
      "nx/core/package-json"
    ],
    "targets.prune-lockfile.options": [
      "apps/api/package.json",
      "nx/core/package-json"
    ],
    "targets.prune-lockfile.options.buildTarget": [
      "apps/api/package.json",
      "nx/core/package-json"
    ],
    "targets.copy-workspace-modules": [
      "apps/api/package.json",
      "nx/core/package-json"
    ],
    "targets.copy-workspace-modules.dependsOn": [
      "apps/api/package.json",
      "nx/core/package-json"
    ],
    "targets.copy-workspace-modules.cache": [
      "apps/api/package.json",
      "nx/core/package-json"
    ],
    "targets.copy-workspace-modules.outputs": [
      "apps/api/package.json",
      "nx/core/package-json"
    ],
    "targets.copy-workspace-modules.executor": [
      "apps/api/package.json",
      "nx/core/package-json"
    ],
    "targets.copy-workspace-modules.options": [
      "apps/api/package.json",
      "nx/core/package-json"
    ],
    "targets.copy-workspace-modules.options.buildTarget": [
      "apps/api/package.json",
      "nx/core/package-json"
    ],
    "targets.prune": [
      "apps/api/package.json",
      "nx/core/package-json"
    ],
    "targets.prune.dependsOn": [
      "apps/api/package.json",
      "nx/core/package-json"
    ],
    "targets.prune.executor": [
      "apps/api/package.json",
      "nx/core/package-json"
    ],
    "targets.serve": [
      "apps/api/package.json",
      "nx/core/package-json"
    ],
    "targets.serve.continuous": [
      "apps/api/package.json",
      "nx/core/package-json"
    ],
    "targets.serve.executor": [
      "apps/api/package.json",
      "nx/core/package-json"
    ],
    "targets.serve.defaultConfiguration": [
      "apps/api/package.json",
      "nx/core/package-json"
    ],
    "targets.serve.dependsOn": [
      "apps/api/package.json",
      "nx/core/package-json"
    ],
    "targets.serve.options": [
      "apps/api/package.json",
      "nx/core/package-json"
    ],
    "targets.serve.configurations": [
      "apps/api/package.json",
      "nx/core/package-json"
    ],
    "targets.serve.options.buildTarget": [
      "apps/api/package.json",
      "nx/core/package-json"
    ],
    "targets.serve.options.runBuildTargetDependencies": [
      "apps/api/package.json",
      "nx/core/package-json"
    ],
    "targets.serve.configurations.development": [
      "apps/api/package.json",
      "nx/core/package-json"
    ],
    "targets.serve.configurations.development.buildTarget": [
      "apps/api/package.json",
      "nx/core/package-json"
    ],
    "targets.serve.configurations.production": [
      "apps/api/package.json",
      "nx/core/package-json"
    ],
    "targets.serve.configurations.production.buildTarget": [
      "apps/api/package.json",
      "nx/core/package-json"
    ]
  },
  "apps/api-e2e": {
    "root": [
      "apps/api-e2e/package.json",
      "nx/core/package-json"
    ],
    "targets": [
      "apps/api-e2e/tsconfig.json",
      "@nx/js/typescript"
    ],
    "targets.typecheck": [
      "apps/api-e2e/tsconfig.json",
      "@nx/js/typescript"
    ],
    "targets.typecheck.dependsOn": [
      "apps/api-e2e/tsconfig.json",
      "@nx/js/typescript"
    ],
    "targets.typecheck.options": [
      "apps/api-e2e/tsconfig.json",
      "@nx/js/typescript"
    ],
    "targets.typecheck.cache": [
      "apps/api-e2e/tsconfig.json",
      "@nx/js/typescript"
    ],
    "targets.typecheck.inputs": [
      "apps/api-e2e/tsconfig.json",
      "@nx/js/typescript"
    ],
    "targets.typecheck.outputs": [
      "apps/api-e2e/tsconfig.json",
      "@nx/js/typescript"
    ],
    "targets.typecheck.syncGenerators": [
      "apps/api-e2e/tsconfig.json",
      "@nx/js/typescript"
    ],
    "targets.typecheck.metadata": [
      "apps/api-e2e/tsconfig.json",
      "@nx/js/typescript"
    ],
    "targets.typecheck.executor": [
      "apps/api-e2e/tsconfig.json",
      "@nx/js/typescript"
    ],
    "targets.typecheck.options.cwd": [
      "apps/api-e2e/tsconfig.json",
      "@nx/js/typescript"
    ],
    "targets.typecheck.options.command": [
      "apps/api-e2e/tsconfig.json",
      "@nx/js/typescript"
    ],
    "targets.typecheck.metadata.technologies": [
      "apps/api-e2e/tsconfig.json",
      "@nx/js/typescript"
    ],
    "targets.typecheck.metadata.technologies.0": [
      "apps/api-e2e/tsconfig.json",
      "@nx/js/typescript"
    ],
    "targets.typecheck.metadata.description": [
      "apps/api-e2e/tsconfig.json",
      "@nx/js/typescript"
    ],
    "targets.typecheck.metadata.help": [
      "apps/api-e2e/tsconfig.json",
      "@nx/js/typescript"
    ],
    "targets.typecheck.metadata.help.command": [
      "apps/api-e2e/tsconfig.json",
      "@nx/js/typescript"
    ],
    "targets.typecheck.metadata.help.example": [
      "apps/api-e2e/tsconfig.json",
      "@nx/js/typescript"
    ],
    "name": [
      "apps/api-e2e/package.json",
      "nx/core/package-json"
    ],
    "tags": [
      "apps/api-e2e/package.json",
      "nx/core/package-json"
    ],
    "tags.npm:private": [
      "apps/api-e2e/package.json",
      "nx/core/package-json"
    ],
    "implicitDependencies": [
      "apps/api-e2e/package.json",
      "nx/core/package-json"
    ],
    "implicitDependencies.@luminalm/api": [
      "apps/api-e2e/package.json",
      "nx/core/package-json"
    ],
    "metadata.targetGroups": [
      "apps/api-e2e/package.json",
      "nx/core/package-json"
    ],
    "metadata.js": [
      "apps/api-e2e/package.json",
      "nx/core/package-json"
    ],
    "metadata.js.packageName": [
      "apps/api-e2e/package.json",
      "nx/core/package-json"
    ],
    "metadata.js.packageVersion": [
      "apps/api-e2e/package.json",
      "nx/core/package-json"
    ],
    "metadata.js.isInPackageManagerWorkspaces": [
      "apps/api-e2e/package.json",
      "nx/core/package-json"
    ],
    "targets.e2e": [
      "apps/api-e2e/package.json",
      "nx/core/package-json"
    ],
    "targets.e2e.executor": [
      "apps/api-e2e/package.json",
      "nx/core/package-json"
    ],
    "targets.e2e.outputs": [
      "apps/api-e2e/package.json",
      "nx/core/package-json"
    ],
    "targets.e2e.options": [
      "apps/api-e2e/package.json",
      "nx/core/package-json"
    ],
    "targets.e2e.dependsOn": [
      "apps/api-e2e/package.json",
      "nx/core/package-json"
    ],
    "targets.e2e.options.jestConfig": [
      "apps/api-e2e/package.json",
      "nx/core/package-json"
    ],
    "targets.e2e.options.passWithNoTests": [
      "apps/api-e2e/package.json",
      "nx/core/package-json"
    ]
  },
  "apps/web-e2e": {
    "root": [
      "apps/web-e2e/package.json",
      "nx/core/package-json"
    ],
    "targets": [
      "apps/web-e2e/tsconfig.json",
      "@nx/js/typescript"
    ],
    "targets.typecheck": [
      "apps/web-e2e/tsconfig.json",
      "@nx/js/typescript"
    ],
    "targets.typecheck.dependsOn": [
      "apps/web-e2e/tsconfig.json",
      "@nx/js/typescript"
    ],
    "targets.typecheck.options": [
      "apps/web-e2e/tsconfig.json",
      "@nx/js/typescript"
    ],
    "targets.typecheck.cache": [
      "apps/web-e2e/tsconfig.json",
      "@nx/js/typescript"
    ],
    "targets.typecheck.inputs": [
      "apps/web-e2e/tsconfig.json",
      "@nx/js/typescript"
    ],
    "targets.typecheck.outputs": [
      "apps/web-e2e/tsconfig.json",
      "@nx/js/typescript"
    ],
    "targets.typecheck.syncGenerators": [
      "apps/web-e2e/tsconfig.json",
      "@nx/js/typescript"
    ],
    "targets.typecheck.metadata": [
      "apps/web-e2e/tsconfig.json",
      "@nx/js/typescript"
    ],
    "targets.typecheck.executor": [
      "apps/web-e2e/tsconfig.json",
      "@nx/js/typescript"
    ],
    "targets.typecheck.options.cwd": [
      "apps/web-e2e/tsconfig.json",
      "@nx/js/typescript"
    ],
    "targets.typecheck.options.command": [
      "apps/web-e2e/tsconfig.json",
      "@nx/js/typescript"
    ],
    "targets.typecheck.metadata.technologies": [
      "apps/web-e2e/tsconfig.json",
      "@nx/js/typescript"
    ],
    "targets.typecheck.metadata.technologies.0": [
      "apps/web-e2e/tsconfig.json",
      "@nx/js/typescript"
    ],
    "targets.typecheck.metadata.description": [
      "apps/web-e2e/tsconfig.json",
      "@nx/js/typescript"
    ],
    "targets.typecheck.metadata.help": [
      "apps/web-e2e/tsconfig.json",
      "@nx/js/typescript"
    ],
    "targets.typecheck.metadata.help.command": [
      "apps/web-e2e/tsconfig.json",
      "@nx/js/typescript"
    ],
    "targets.typecheck.metadata.help.example": [
      "apps/web-e2e/tsconfig.json",
      "@nx/js/typescript"
    ],
    "metadata.targetGroups": [
      "apps/web-e2e/playwright.config.ts",
      "@nx/playwright/plugin"
    ],
    "metadata.targetGroups.E2E (CI)": [
      "apps/web-e2e/playwright.config.ts",
      "@nx/playwright/plugin"
    ],
    "metadata.targetGroups.E2E (CI).0": [
      "apps/web-e2e/playwright.config.ts",
      "@nx/playwright/plugin"
    ],
    "metadata.targetGroups.E2E (CI).1": [
      "apps/web-e2e/playwright.config.ts",
      "@nx/playwright/plugin"
    ],
    "metadata.targetGroups.E2E (CI).2": [
      "apps/web-e2e/playwright.config.ts",
      "@nx/playwright/plugin"
    ],
    "targets.e2e": [
      "apps/web-e2e/playwright.config.ts",
      "@nx/playwright/plugin"
    ],
    "targets.e2e.options": [
      "apps/web-e2e/playwright.config.ts",
      "@nx/playwright/plugin"
    ],
    "targets.e2e.metadata": [
      "apps/web-e2e/playwright.config.ts",
      "@nx/playwright/plugin"
    ],
    "targets.e2e.dependsOn": [
      "apps/web-e2e/playwright.config.ts",
      "@nx/playwright/plugin"
    ],
    "targets.e2e.cache": [
      "apps/web-e2e/playwright.config.ts",
      "@nx/playwright/plugin"
    ],
    "targets.e2e.inputs": [
      "apps/web-e2e/playwright.config.ts",
      "@nx/playwright/plugin"
    ],
    "targets.e2e.outputs": [
      "apps/web-e2e/playwright.config.ts",
      "@nx/playwright/plugin"
    ],
    "targets.e2e.executor": [
      "apps/web-e2e/playwright.config.ts",
      "@nx/playwright/plugin"
    ],
    "targets.e2e.options.cwd": [
      "apps/web-e2e/playwright.config.ts",
      "@nx/playwright/plugin"
    ],
    "targets.e2e.options.command": [
      "apps/web-e2e/playwright.config.ts",
      "@nx/playwright/plugin"
    ],
    "targets.e2e.metadata.technologies": [
      "apps/web-e2e/playwright.config.ts",
      "@nx/playwright/plugin"
    ],
    "targets.e2e.metadata.technologies.0": [
      "apps/web-e2e/playwright.config.ts",
      "@nx/playwright/plugin"
    ],
    "targets.e2e.metadata.description": [
      "apps/web-e2e/playwright.config.ts",
      "@nx/playwright/plugin"
    ],
    "targets.e2e.metadata.help": [
      "apps/web-e2e/playwright.config.ts",
      "@nx/playwright/plugin"
    ],
    "targets.e2e.metadata.help.command": [
      "apps/web-e2e/playwright.config.ts",
      "@nx/playwright/plugin"
    ],
    "targets.e2e.metadata.help.example": [
      "apps/web-e2e/playwright.config.ts",
      "@nx/playwright/plugin"
    ],
    "targets.e2e-ci--src/example.spec.ts": [
      "apps/web-e2e/playwright.config.ts",
      "@nx/playwright/plugin"
    ],
    "targets.e2e-ci--src/example.spec.ts.options": [
      "apps/web-e2e/playwright.config.ts",
      "@nx/playwright/plugin"
    ],
    "targets.e2e-ci--src/example.spec.ts.metadata": [
      "apps/web-e2e/playwright.config.ts",
      "@nx/playwright/plugin"
    ],
    "targets.e2e-ci--src/example.spec.ts.dependsOn": [
      "apps/web-e2e/playwright.config.ts",
      "@nx/playwright/plugin"
    ],
    "targets.e2e-ci--src/example.spec.ts.cache": [
      "apps/web-e2e/playwright.config.ts",
      "@nx/playwright/plugin"
    ],
    "targets.e2e-ci--src/example.spec.ts.inputs": [
      "apps/web-e2e/playwright.config.ts",
      "@nx/playwright/plugin"
    ],
    "targets.e2e-ci--src/example.spec.ts.outputs": [
      "apps/web-e2e/playwright.config.ts",
      "@nx/playwright/plugin"
    ],
    "targets.e2e-ci--src/example.spec.ts.executor": [
      "apps/web-e2e/playwright.config.ts",
      "@nx/playwright/plugin"
    ],
    "targets.e2e-ci--src/example.spec.ts.options.cwd": [
      "apps/web-e2e/playwright.config.ts",
      "@nx/playwright/plugin"
    ],
    "targets.e2e-ci--src/example.spec.ts.options.env": [
      "apps/web-e2e/playwright.config.ts",
      "@nx/playwright/plugin"
    ],
    "targets.e2e-ci--src/example.spec.ts.options.command": [
      "apps/web-e2e/playwright.config.ts",
      "@nx/playwright/plugin"
    ],
    "targets.e2e-ci--src/example.spec.ts.metadata.technologies": [
      "apps/web-e2e/playwright.config.ts",
      "@nx/playwright/plugin"
    ],
    "targets.e2e-ci--src/example.spec.ts.metadata.technologies.0": [
      "apps/web-e2e/playwright.config.ts",
      "@nx/playwright/plugin"
    ],
    "targets.e2e-ci--src/example.spec.ts.metadata.description": [
      "apps/web-e2e/playwright.config.ts",
      "@nx/playwright/plugin"
    ],
    "targets.e2e-ci--src/example.spec.ts.metadata.help": [
      "apps/web-e2e/playwright.config.ts",
      "@nx/playwright/plugin"
    ],
    "targets.e2e-ci--src/example.spec.ts.metadata.help.command": [
      "apps/web-e2e/playwright.config.ts",
      "@nx/playwright/plugin"
    ],
    "targets.e2e-ci--src/example.spec.ts.metadata.help.example": [
      "apps/web-e2e/playwright.config.ts",
      "@nx/playwright/plugin"
    ],
    "targets.e2e-ci": [
      "apps/web-e2e/playwright.config.ts",
      "@nx/playwright/plugin"
    ],
    "targets.e2e-ci.executor": [
      "apps/web-e2e/playwright.config.ts",
      "@nx/playwright/plugin"
    ],
    "targets.e2e-ci.cache": [
      "apps/web-e2e/playwright.config.ts",
      "@nx/playwright/plugin"
    ],
    "targets.e2e-ci.inputs": [
      "apps/web-e2e/playwright.config.ts",
      "@nx/playwright/plugin"
    ],
    "targets.e2e-ci.outputs": [
      "apps/web-e2e/playwright.config.ts",
      "@nx/playwright/plugin"
    ],
    "targets.e2e-ci.dependsOn": [
      "apps/web-e2e/playwright.config.ts",
      "@nx/playwright/plugin"
    ],
    "targets.e2e-ci.metadata": [
      "apps/web-e2e/playwright.config.ts",
      "@nx/playwright/plugin"
    ],
    "targets.e2e-ci.metadata.technologies": [
      "apps/web-e2e/playwright.config.ts",
      "@nx/playwright/plugin"
    ],
    "targets.e2e-ci.metadata.technologies.0": [
      "apps/web-e2e/playwright.config.ts",
      "@nx/playwright/plugin"
    ],
    "targets.e2e-ci.metadata.description": [
      "apps/web-e2e/playwright.config.ts",
      "@nx/playwright/plugin"
    ],
    "targets.e2e-ci.metadata.nonAtomizedTarget": [
      "apps/web-e2e/playwright.config.ts",
      "@nx/playwright/plugin"
    ],
    "targets.e2e-ci.metadata.help": [
      "apps/web-e2e/playwright.config.ts",
      "@nx/playwright/plugin"
    ],
    "targets.e2e-ci.metadata.help.command": [
      "apps/web-e2e/playwright.config.ts",
      "@nx/playwright/plugin"
    ],
    "targets.e2e-ci.metadata.help.example": [
      "apps/web-e2e/playwright.config.ts",
      "@nx/playwright/plugin"
    ],
    "targets.e2e-ci--merge-reports": [
      "apps/web-e2e/playwright.config.ts",
      "@nx/playwright/plugin"
    ],
    "targets.e2e-ci--merge-reports.executor": [
      "apps/web-e2e/playwright.config.ts",
      "@nx/playwright/plugin"
    ],
    "targets.e2e-ci--merge-reports.cache": [
      "apps/web-e2e/playwright.config.ts",
      "@nx/playwright/plugin"
    ],
    "targets.e2e-ci--merge-reports.inputs": [
      "apps/web-e2e/playwright.config.ts",
      "@nx/playwright/plugin"
    ],
    "targets.e2e-ci--merge-reports.outputs": [
      "apps/web-e2e/playwright.config.ts",
      "@nx/playwright/plugin"
    ],
    "targets.e2e-ci--merge-reports.options": [
      "apps/web-e2e/playwright.config.ts",
      "@nx/playwright/plugin"
    ],
    "targets.e2e-ci--merge-reports.metadata": [
      "apps/web-e2e/playwright.config.ts",
      "@nx/playwright/plugin"
    ],
    "targets.e2e-ci--merge-reports.options.config": [
      "apps/web-e2e/playwright.config.ts",
      "@nx/playwright/plugin"
    ],
    "targets.e2e-ci--merge-reports.options.expectedSuites": [
      "apps/web-e2e/playwright.config.ts",
      "@nx/playwright/plugin"
    ],
    "targets.e2e-ci--merge-reports.metadata.technologies": [
      "apps/web-e2e/playwright.config.ts",
      "@nx/playwright/plugin"
    ],
    "targets.e2e-ci--merge-reports.metadata.technologies.0": [
      "apps/web-e2e/playwright.config.ts",
      "@nx/playwright/plugin"
    ],
    "targets.e2e-ci--merge-reports.metadata.description": [
      "apps/web-e2e/playwright.config.ts",
      "@nx/playwright/plugin"
    ],
    "name": [
      "apps/web-e2e/package.json",
      "nx/core/package-json"
    ],
    "tags": [
      "apps/web-e2e/package.json",
      "nx/core/package-json"
    ],
    "tags.npm:private": [
      "apps/web-e2e/package.json",
      "nx/core/package-json"
    ],
    "implicitDependencies": [
      "apps/web-e2e/package.json",
      "nx/core/package-json"
    ],
    "implicitDependencies.@luminalm/web": [
      "apps/web-e2e/package.json",
      "nx/core/package-json"
    ],
    "metadata.js": [
      "apps/web-e2e/package.json",
      "nx/core/package-json"
    ],
    "metadata.js.packageName": [
      "apps/web-e2e/package.json",
      "nx/core/package-json"
    ],
    "metadata.js.packageVersion": [
      "apps/web-e2e/package.json",
      "nx/core/package-json"
    ],
    "metadata.js.isInPackageManagerWorkspaces": [
      "apps/web-e2e/package.json",
      "nx/core/package-json"
    ]
  },
  "apps/web": {
    "root": [
      "apps/web/package.json",
      "nx/core/package-json"
    ],
    "targets": [
      "apps/web/next.config.js",
      "@nx/next/plugin"
    ],
    "targets.build": [
      "apps/web/next.config.js",
      "@nx/next/plugin"
    ],
    "targets.build.options": [
      "apps/web/next.config.js",
      "@nx/next/plugin"
    ],
    "targets.build.dependsOn": [
      "apps/web/next.config.js",
      "@nx/next/plugin"
    ],
    "targets.build.cache": [
      "apps/web/next.config.js",
      "@nx/next/plugin"
    ],
    "targets.build.inputs": [
      "apps/web/next.config.js",
      "@nx/next/plugin"
    ],
    "targets.build.outputs": [
      "apps/web/next.config.js",
      "@nx/next/plugin"
    ],
    "targets.build.syncGenerators": [
      "apps/web/next.config.js",
      "@nx/next/plugin"
    ],
    "targets.build.executor": [
      "apps/web/next.config.js",
      "@nx/next/plugin"
    ],
    "targets.build.options.cwd": [
      "apps/web/next.config.js",
      "@nx/next/plugin"
    ],
    "targets.build.options.tty": [
      "apps/web/next.config.js",
      "@nx/next/plugin"
    ],
    "targets.build.options.command": [
      "apps/web/next.config.js",
      "@nx/next/plugin"
    ],
    "targets.dev": [
      "apps/web/package.json",
      "nx/core/package-json"
    ],
    "targets.dev.continuous": [
      "apps/web/next.config.js",
      "@nx/next/plugin"
    ],
    "targets.dev.options": [
      "apps/web/package.json",
      "nx/core/package-json"
    ],
    "targets.dev.syncGenerators": [
      "apps/web/next.config.js",
      "@nx/next/plugin"
    ],
    "targets.dev.executor": [
      "apps/web/next.config.js",
      "@nx/next/plugin"
    ],
    "targets.dev.options.cwd": [
      "apps/web/next.config.js",
      "@nx/next/plugin"
    ],
    "targets.dev.options.command": [
      "apps/web/next.config.js",
      "@nx/next/plugin"
    ],
    "targets.start": [
      "apps/web/next.config.js",
      "@nx/next/plugin"
    ],
    "targets.start.continuous": [
      "apps/web/next.config.js",
      "@nx/next/plugin"
    ],
    "targets.start.options": [
      "apps/web/next.config.js",
      "@nx/next/plugin"
    ],
    "targets.start.dependsOn": [
      "apps/web/next.config.js",
      "@nx/next/plugin"
    ],
    "targets.start.executor": [
      "apps/web/next.config.js",
      "@nx/next/plugin"
    ],
    "targets.start.options.cwd": [
      "apps/web/next.config.js",
      "@nx/next/plugin"
    ],
    "targets.start.options.command": [
      "apps/web/next.config.js",
      "@nx/next/plugin"
    ],
    "targets.serve-static": [
      "apps/web/next.config.js",
      "@nx/next/plugin"
    ],
    "targets.serve-static.continuous": [
      "apps/web/next.config.js",
      "@nx/next/plugin"
    ],
    "targets.serve-static.options": [
      "apps/web/next.config.js",
      "@nx/next/plugin"
    ],
    "targets.serve-static.dependsOn": [
      "apps/web/next.config.js",
      "@nx/next/plugin"
    ],
    "targets.serve-static.executor": [
      "apps/web/next.config.js",
      "@nx/next/plugin"
    ],
    "targets.serve-static.options.cwd": [
      "apps/web/next.config.js",
      "@nx/next/plugin"
    ],
    "targets.serve-static.options.command": [
      "apps/web/next.config.js",
      "@nx/next/plugin"
    ],
    "targets.build-deps": [
      "apps/web/next.config.js",
      "@nx/next/plugin"
    ],
    "targets.build-deps.dependsOn": [
      "apps/web/next.config.js",
      "@nx/next/plugin"
    ],
    "targets.watch-deps": [
      "apps/web/next.config.js",
      "@nx/next/plugin"
    ],
    "targets.watch-deps.continuous": [
      "apps/web/next.config.js",
      "@nx/next/plugin"
    ],
    "targets.watch-deps.dependsOn": [
      "apps/web/next.config.js",
      "@nx/next/plugin"
    ],
    "targets.watch-deps.executor": [
      "apps/web/next.config.js",
      "@nx/next/plugin"
    ],
    "targets.watch-deps.options": [
      "apps/web/next.config.js",
      "@nx/next/plugin"
    ],
    "targets.watch-deps.options.command": [
      "apps/web/next.config.js",
      "@nx/next/plugin"
    ],
    "name": [
      "apps/web/package.json",
      "nx/core/package-json"
    ],
    "tags": [
      "apps/web/package.json",
      "nx/core/package-json"
    ],
    "tags.npm:private": [
      "apps/web/package.json",
      "nx/core/package-json"
    ],
    "metadata.targetGroups": [
      "apps/web/package.json",
      "nx/core/package-json"
    ],
    "metadata.js": [
      "apps/web/package.json",
      "nx/core/package-json"
    ],
    "metadata.js.packageName": [
      "apps/web/package.json",
      "nx/core/package-json"
    ],
    "metadata.js.packageVersion": [
      "apps/web/package.json",
      "nx/core/package-json"
    ],
    "metadata.js.isInPackageManagerWorkspaces": [
      "apps/web/package.json",
      "nx/core/package-json"
    ],
    "targets.dev.options.port": [
      "apps/web/package.json",
      "nx/core/package-json"
    ]
  }
}